LICENSE
LICENSE.txt
README.rst
setup.cfg
setup.py
MyBuiler/__init__.py
MyBuiler/builder.py
MyBuiler.egg-info/PKG-INFO
MyBuiler.egg-info/SOURCES.txt
MyBuiler.egg-info/dependency_links.txt
MyBuiler.egg-info/top_level.txt